chain_semantic_splitter/__init__.py
chain_semantic_splitter/splitter.py
chain_semantic_splitter-0.2.7.dist-info/METADATA
chain_semantic_splitter-0.2.7.dist-info/WHEEL
chain_semantic_splitter-0.2.7.dist-info/licenses/LICENSE
chain_semantic_splitter-0.2.7.dist-info/RECORD
