Metadata-Version: 2.4
Name: chain-semantic-splitter
Version: 0.2.7
Summary: A LangChain TextSplitter that uses semantic understanding to intelligently merge text chunks.
Project-URL: Homepage, https://github.com/sitrakaherivalisoagithub/chain-semantic-splitter.git
Project-URL: Repository, https://github.com/sitrakaherivalisoagithub/chain-semantic-splitter.git
Author: Sitraka Herivalsoa
License: MIT
License-File: LICENSE
Classifier: Development Status :: 3 - Alpha
Classifier: Intended Audience :: Developers
Classifier: License :: OSI Approved :: MIT License
Classifier: Programming Language :: Python :: 3
Classifier: Programming Language :: Python :: 3.10
Classifier: Programming Language :: Python :: 3.11
Classifier: Programming Language :: Python :: 3.12
Classifier: Topic :: Software Development :: Libraries :: Python Modules
Classifier: Topic :: Text Processing :: General
Requires-Python: >=3.10
Requires-Dist: langchain-core<0.2.0,>=0.1.40
Requires-Dist: langchain<0.2.0,>=0.1.16
